django_template_breakpoint/__init__.py
django_template_breakpoint/templatetags/__init__.py
django_template_breakpoint/templatetags/breakpoint.py
django_template_breakpoint-0.0.1.dist-info/LICENSE
django_template_breakpoint-0.0.1.dist-info/WHEEL
django_template_breakpoint-0.0.1.dist-info/METADATA
django_template_breakpoint-0.0.1.dist-info/RECORD
