Metadata-Version: 2.1
Name: django_template_breakpoint
Version: 0.0.1
Summary: A template tag for dropping into a debugger inside a Django template.
Author-email: Peter Inglesby <peter.inglesby@gmail.com>
Requires-Python: >=3.7
Classifier: License :: OSI Approved :: MIT License
Requires-Dist: django
Requires-Dist: pytest ; extra == "test"
Project-URL: Source, https://github.com/inglesp/django-template-breakpoint
Provides-Extra: test
